win32_classics/__init__.py
win32_classics/fenster_aktionen.py
win32_classics-0.0.7.dist-info/LICENSE
win32_classics-0.0.7.dist-info/METADATA
win32_classics-0.0.7.dist-info/WHEEL
win32_classics-0.0.7.dist-info/top_level.txt
win32_classics-0.0.7.dist-info/RECORD
