Metadata-Version: 2.1
Name: win32-classics
Version: 0.0.7
Summary: Simplify win32 actions
Author: André Herber
Author-email: andre.herber.programming@gmail.com
Keywords: python
Classifier: Development Status :: 1 - Planning
Classifier: Intended Audience :: Developers
Classifier: Programming Language :: Python :: 3
Classifier: Operating System :: Unix
Classifier: Operating System :: MacOS :: MacOS X
Classifier: Operating System :: Microsoft :: Windows
License-File: LICENSE
Requires-Dist: pywin32
Requires-Dist: screeninfo
Requires-Dist: colorful-terminal
Requires-Dist: exception-details
